swissroll/__init__.py
swissroll/_distribution.py
swissroll/distributions.py
swissroll/gaussian_process.py
swissroll/gmm.py
swissroll/plotter.py
swissroll/utils.py
swissroll-1.0.4.dist-info/LICENSE
swissroll-1.0.4.dist-info/METADATA
swissroll-1.0.4.dist-info/WHEEL
swissroll-1.0.4.dist-info/top_level.txt
swissroll-1.0.4.dist-info/RECORD
