Metadata-Version: 2.1
Name: swissroll
Version: 1.0.4
Summary: Higher Level API for working with Probability Distributions.
Home-page: https://github.com/tirthasheshpatel/swissroll
Author: Tirth Patel and GitHub Community
Author-email: tirthasheshpatel@gmail.com
License: BSD-3-Clause
Platform: UNKNOWN
Classifier: License :: OSI Approved :: BSD License
Classifier: Programming Language :: Python :: 3.6
Classifier: Programming Language :: Python :: 3.7
Requires-Dist: numpy
Requires-Dist: scipy
Requires-Dist: matplotlib
Requires-Dist: sklearn
